MANIFEST.in
l10n_si_wizard.xml
setup.py
./__init__.py
./__openerp__.py
./account_wizard.py
data/account.account.template.csv
data/account.account.type.csv
data/account.chart.template.csv
data/account.fiscal.position.account.template.csv
data/account.fiscal.position.tax.template.csv
data/account.fiscal.position.template.csv
data/account.tax.code.template.csv
data/account.tax.template.csv
openerp_l10n_si.egg-info/PKG-INFO
openerp_l10n_si.egg-info/SOURCES.txt
openerp_l10n_si.egg-info/dependency_links.txt
openerp_l10n_si.egg-info/requires.txt
openerp_l10n_si.egg-info/top_level.txt
static/src/img/icon.png